raglite/__init__.py
raglite/_bench.py
raglite/_chainlit.py
raglite/_chatml_function_calling.py
raglite/_cli.py
raglite/_config.py
raglite/_database.py
raglite/_embed.py
raglite/_eval.py
raglite/_extract.py
raglite/_insert.py
raglite/_lazy_llama.py
raglite/_litellm.py
raglite/_markdown.py
raglite/_mcp.py
raglite/_query_adapter.py
raglite/_rag.py
raglite/_search.py
raglite/_split_chunklets.py
raglite/_split_chunks.py
raglite/_split_sentences.py
raglite/_typing.py
raglite/py.typed
raglite-1.0.0.dist-info/METADATA
raglite-1.0.0.dist-info/WHEEL
raglite-1.0.0.dist-info/entry_points.txt
raglite-1.0.0.dist-info/licenses/LICENSE
raglite-1.0.0.dist-info/RECORD
