Metadata-Version: 2.4
Name: raglite
Version: 1.0.0
Summary: A Python toolkit for Retrieval-Augmented Generation (RAG) with DuckDB or PostgreSQL.
Project-URL: homepage, https://github.com/superlinear-ai/raglite
Project-URL: source, https://github.com/superlinear-ai/raglite
Project-URL: changelog, https://github.com/superlinear-ai/raglite/blob/main/CHANGELOG.md
Project-URL: releasenotes, https://github.com/superlinear-ai/raglite/releases
Project-URL: documentation, https://github.com/superlinear-ai/raglite
Project-URL: issues, https://github.com/superlinear-ai/raglite/issues
Author-email: Laurent Sorber <laurent@superlinear.eu>
License-File: LICENSE
Requires-Python: <4.0,>=3.10
Requires-Dist: duckdb-engine>=0.16.0
Requires-Dist: duckdb>=1.1.3
Requires-Dist: fastmcp>=2.0.0
Requires-Dist: huggingface-hub>=0.31.2
Requires-Dist: langdetect>=1.0.9
Requires-Dist: litellm>=1.60.2
Requires-Dist: markdown-it-py>=3.0.0
Requires-Dist: numpy<2.0.0,>=1.26.4
Requires-Dist: packaging>=23.0
Requires-Dist: pdftext>=0.4.1
Requires-Dist: pg8000>=1.31.2
Requires-Dist: platformdirs>=4.0.0
Requires-Dist: pydantic>=2.7.0
Requires-Dist: rerankers[api,flashrank]>=0.10.0
Requires-Dist: scikit-learn>=1.4.2
Requires-Dist: scipy!=1.15.0.*,!=1.15.1,!=1.15.2,>=1.11.2
Requires-Dist: sqlmodel-slim>=0.0.21
Requires-Dist: tqdm>=4.66.0
Requires-Dist: typer>=0.15.1
Requires-Dist: wtpsplit-lite>=0.1.0
Provides-Extra: bench
Requires-Dist: faiss-cpu>=1.11.0; extra == 'bench'
Requires-Dist: ir-datasets>=0.5.10; extra == 'bench'
Requires-Dist: ir-measures>=0.3.7; extra == 'bench'
Requires-Dist: llama-index-vector-stores-faiss>=0.4.0; extra == 'bench'
Requires-Dist: llama-index>=0.12.39; extra == 'bench'
Requires-Dist: openai>=1.75.0; extra == 'bench'
Requires-Dist: pandas>=2.1.1; extra == 'bench'
Requires-Dist: python-slugify>=8.0.4; extra == 'bench'
Provides-Extra: chainlit
Requires-Dist: chainlit>=2.0.0; extra == 'chainlit'
Provides-Extra: llama-cpp-python
Requires-Dist: llama-cpp-python>=0.3.9; extra == 'llama-cpp-python'
Provides-Extra: pandoc
Requires-Dist: pypandoc-binary>=1.13; extra == 'pandoc'
Provides-Extra: ragas
Requires-Dist: pandas>=2.1.1; extra == 'ragas'
Requires-Dist: ragas>=0.1.12; extra == 'ragas'
